setup.py
aw_distributions.egg-info/PKG-INFO
aw_distributions.egg-info/SOURCES.txt
aw_distributions.egg-info/dependency_links.txt
aw_distributions.egg-info/not-zip-safe
aw_distributions.egg-info/top_level.txt
distributions/Binomialdistribution.py
distributions/Gaussiandistribution.py
distributions/Generaldistribution.py
distributions/__init__.py