Metadata-Version: 1.0
Name: aw-distributions
Version: 0.1
Summary: Gaussian distributions
Home-page: UNKNOWN
Author: Wah Chi Shing
Author-email: wahchishing@gmail.com
License: UNKNOWN
Platform: UNKNOWN
